falcon_caching/__init__.py
falcon_caching/async_cache.py
falcon_caching/async_middleware.py
falcon_caching/async_utils.py
falcon_caching/cache.py
falcon_caching/middleware.py
falcon_caching/options.py
falcon_caching/utils.py
falcon_caching/async_backends/__init__.py
falcon_caching/async_backends/base.py
falcon_caching/async_backends/filesystem.py
falcon_caching/async_backends/memcache.py
falcon_caching/async_backends/null.py
falcon_caching/async_backends/redis.py
falcon_caching/async_backends/simple.py
falcon_caching/backends/__init__.py
falcon_caching/backends/base.py
falcon_caching/backends/filesystem.py
falcon_caching/backends/memcache.py
falcon_caching/backends/null.py
falcon_caching/backends/redis.py
falcon_caching/backends/simple.py
falcon_caching/backends/uwsgicache.py
falcon_caching-1.1.0.dist-info/LICENSE
falcon_caching-1.1.0.dist-info/WHEEL
falcon_caching-1.1.0.dist-info/METADATA
falcon_caching-1.1.0.dist-info/RECORD
