Metadata-Version: 2.1
Name: falcon-caching
Version: 1.1.0
Summary: Falcon-Caching - a caching module for the Falcon web framework
Home-page: https://github.com/zoltan-fedor/falcon-caching
Author: Zoltan Fedor
Author-email: zoltan.1.fedor@gmail.com
Requires-Python: >=3.7
Classifier: Development Status :: 4 - Beta
Classifier: Environment :: Web Environment
Classifier: License :: OSI Approved :: MIT License
Classifier: Intended Audience :: Developers
Classifier: Intended Audience :: Information Technology
Classifier: Intended Audience :: System Administrators
Classifier: Operating System :: OS Independent
Classifier: Programming Language :: Python
Classifier: Programming Language :: Python :: 3
Classifier: Programming Language :: Python :: 3.7
Classifier: Programming Language :: Python :: 3.8
Classifier: Programming Language :: Python :: 3.9
Classifier: Programming Language :: Python :: 3.10
Classifier: Programming Language :: Python :: Implementation :: CPython
Classifier: Programming Language :: Python :: Implementation :: PyPy
Classifier: Topic :: Internet :: WWW/HTTP :: Dynamic Content
Classifier: Topic :: Internet :: WWW/HTTP :: WSGI :: Middleware
Classifier: Topic :: Software Development :: Libraries :: Python Modules
Classifier: Typing :: Typed
Requires-Dist: falcon >=1.0.0
Requires-Dist: msgpack
Requires-Dist: aiofiles ; extra == "test"
Requires-Dist: coredis>=3.0.0 ; extra == "test"
Requires-Dist: emcache ; extra == "test"
Requires-Dist: flit ; extra == "test"
Requires-Dist: pylibmc ; extra == "test"
Requires-Dist: pytest >=4.0.0 ; extra == "test"
Requires-Dist: pytest-asyncio ; extra == "test"
Requires-Dist: pytest-cov ; extra == "test"
Requires-Dist: pytest-pep8 ; extra == "test"
Requires-Dist: pytest-xdist ; extra == "test"
Requires-Dist: pytest-xprocess ; extra == "test"
Requires-Dist: redis ; extra == "test"
Requires-Dist: tox ; extra == "test"
Requires-Dist: tox-pipenv-install ; extra == "test"
Project-URL: Documentation, https://falcon-caching.readthedocs.io/en/latest/
Provides-Extra: all
Provides-Extra: dev
Provides-Extra: doc
Provides-Extra: test
